gdeltdoc/__init__.py
gdeltdoc/_version.py
gdeltdoc/api_client.py
gdeltdoc/errors.py
gdeltdoc/filters.py
gdeltdoc/helpers.py
gdeltdoc/validation.py
tests/__init__.py
tests/test_client.py
tests/test_errors.py
tests/test_filters.py
tests/test_helpers.py
tests/test_validation.py
gdeltdoc-1.12.0.dist-info/LICENSE
gdeltdoc-1.12.0.dist-info/METADATA
gdeltdoc-1.12.0.dist-info/WHEEL
gdeltdoc-1.12.0.dist-info/top_level.txt
gdeltdoc-1.12.0.dist-info/RECORD
