Metadata-Version: 2.1
Name: gdeltdoc
Version: 1.12.0
Summary: A client for the GDELT 2.0 Doc API
Home-page: https://github.com/alex9smith/gdelt-doc-api
Author: Alex Whitehead-Smith
Author-email: alex.me.smith@gmail.com
License: UNKNOWN
Platform: UNKNOWN
Classifier: Programming Language :: Python :: 3
Classifier: License :: OSI Approved :: MIT License
Classifier: Operating System :: OS Independent
Requires-Python: >=3.10
License-File: LICENSE
